tmengine/__init__.py
tmengine-1.0.1.dist-info/LICENSE
tmengine-1.0.1.dist-info/METADATA
tmengine-1.0.1.dist-info/WHEEL
tmengine-1.0.1.dist-info/top_level.txt
tmengine-1.0.1.dist-info/RECORD
