Metadata-Version: 2.1
Name: tmengine
Version: 1.0.1
Summary: A TextMate grammar engine in Python.
Author-email: Aarav Malani <aarav.malani@gmail.com>
Project-URL: Homepage, https://github.com/AaravMalani/tmengine
Project-URL: Bug Tracker, https://github.com/AaravMalani/tmengine/issues
Classifier: Programming Language :: Python :: 3
Classifier: License :: OSI Approved :: MIT License
Classifier: Operating System :: OS Independent
Requires-Python: >=3.6
License-File: LICENSE
